{
  "generated_at": "2026-06-01T15:12:06.830753Z",
  "lido_buffer_eth": "1922.939732413143584232",
  "lido_withdrawal_queue_eth": "4034.990347799314576262",
  "predictions": [
    {
      "exit_validators": 0,
      "exited_validators": 0,
      "exiting_validators": [],
      "exits_eth": "0",
      "full_withdrawal_validators": 0,
      "label": "06-02",
      "queued_exit_validators": 0,
      "rewards_eth": "343.323586614",
      "target_datetime": "2026-06-02T12:22:11Z",
      "total_eth": "343.323586614",
      "validators": 20542
    },
    {
      "exit_validators": 0,
      "exited_validators": 0,
      "exiting_validators": [],
      "exits_eth": "0",
      "full_withdrawal_validators": 0,
      "label": "06-03",
      "queued_exit_validators": 0,
      "rewards_eth": "436.353110101",
      "target_datetime": "2026-06-03T12:22:11Z",
      "total_eth": "436.353110101",
      "validators": 26875
    },
    {
      "exit_validators": 0,
      "exited_validators": 0,
      "exiting_validators": [],
      "exits_eth": "0",
      "full_withdrawal_validators": 0,
      "label": "06-04",
      "queued_exit_validators": 0,
      "rewards_eth": "525.910818292",
      "target_datetime": "2026-06-04T12:22:11Z",
      "total_eth": "525.910818292",
      "validators": 33942
    },
    {
      "exit_validators": 1052,
      "exited_validators": 705,
      "exiting_validators": [],
      "exits_eth": "33673.165844505",
      "full_withdrawal_validators": 1052,
      "label": "06-05",
      "queued_exit_validators": 347,
      "rewards_eth": "859.295487715",
      "target_datetime": "2026-06-05T12:22:11Z",
      "total_eth": "34532.461332220",
      "validators": 69994
    },
    {
      "exit_validators": 1053,
      "exited_validators": 706,
      "exiting_validators": [],
      "exits_eth": "33705.16976501",
      "full_withdrawal_validators": 1053,
      "label": "06-06",
      "queued_exit_validators": 347,
      "rewards_eth": "1157.562277756",
      "target_datetime": "2026-06-06T12:22:11Z",
      "total_eth": "34862.732042766",
      "validators": 110820
    },
    {
      "exit_validators": 1053,
      "exited_validators": 706,
      "exiting_validators": [],
      "exits_eth": "33705.16976501",
      "full_withdrawal_validators": 1053,
      "label": "06-07",
      "queued_exit_validators": 347,
      "rewards_eth": "1490.6903038",
      "target_datetime": "2026-06-07T12:22:11Z",
      "total_eth": "35195.86006881",
      "validators": 175286
    },
    {
      "exit_validators": 1053,
      "exited_validators": 706,
      "exiting_validators": [],
      "exits_eth": "33705.16976501",
      "full_withdrawal_validators": 1053,
      "label": "06-08",
      "queued_exit_validators": 347,
      "rewards_eth": "1693.20474487",
      "target_datetime": "2026-06-08T12:22:11Z",
      "total_eth": "35398.37450988",
      "validators": 242312
    },
    {
      "exit_validators": 1053,
      "exited_validators": 706,
      "exiting_validators": [],
      "exits_eth": "33705.16976501",
      "full_withdrawal_validators": 1053,
      "label": "06-09",
      "queued_exit_validators": 347,
      "rewards_eth": "1718.721220882",
      "target_datetime": "2026-06-09T12:22:11Z",
      "total_eth": "35423.890985892",
      "validators": 271282
    }
  ],
  "refresh_interval_seconds": 600
}
