{
  "generated_at": "2026-06-05T09:12:31.763056Z",
  "lido_buffer_eth": "42713.118257439675730311",
  "lido_withdrawal_queue_eth": "27841.876930382626874658",
  "predictions": [
    {
      "exit_validators": 0,
      "exited_validators": 0,
      "exiting_validators": [],
      "exits_eth": "0",
      "full_withdrawal_validators": 0,
      "label": "06-05",
      "queued_exit_validators": 0,
      "rewards_eth": "197.91502591",
      "target_datetime": "2026-06-05T12:21:35Z",
      "total_eth": "197.91502591",
      "validators": 11324
    },
    {
      "exit_validators": 153,
      "exited_validators": 153,
      "exiting_validators": [],
      "exits_eth": "4898.080945491",
      "full_withdrawal_validators": 153,
      "label": "06-06",
      "queued_exit_validators": 0,
      "rewards_eth": "813.839847516",
      "target_datetime": "2026-06-06T12:21:35Z",
      "total_eth": "5711.920793007",
      "validators": 49796
    },
    {
      "exit_validators": 153,
      "exited_validators": 153,
      "exiting_validators": [],
      "exits_eth": "4898.080945491",
      "full_withdrawal_validators": 153,
      "label": "06-07",
      "queued_exit_validators": 0,
      "rewards_eth": "1730.365152665",
      "target_datetime": "2026-06-07T12:21:35Z",
      "total_eth": "6628.446098156",
      "validators": 115511
    },
    {
      "exit_validators": 153,
      "exited_validators": 153,
      "exiting_validators": [],
      "exits_eth": "4898.080945491",
      "full_withdrawal_validators": 153,
      "label": "06-08",
      "queued_exit_validators": 0,
      "rewards_eth": "2554.312789003",
      "target_datetime": "2026-06-08T12:21:35Z",
      "total_eth": "7452.393734494",
      "validators": 185613
    },
    {
      "exit_validators": 153,
      "exited_validators": 153,
      "exiting_validators": [],
      "exits_eth": "4898.080945491",
      "full_withdrawal_validators": 153,
      "label": "06-09",
      "queued_exit_validators": 0,
      "rewards_eth": "2917.098955297",
      "target_datetime": "2026-06-09T12:21:35Z",
      "total_eth": "7815.179900788",
      "validators": 224404
    },
    {
      "exit_validators": 156,
      "exited_validators": 153,
      "exiting_validators": [
        {
          "balance_eth": "32.005615441",
          "balance_gwei": "32005615441",
          "effective_balance_eth": "32",
          "effective_balance_gwei": "32000000000",
          "full_balance_available_at_period_end": true,
          "status": "exiting_online",
          "validator_index": 1674865,
          "withdrawable_epoch": 452937
        },
        {
          "balance_eth": "32.005619685",
          "balance_gwei": "32005619685",
          "effective_balance_eth": "32",
          "effective_balance_gwei": "32000000000",
          "full_balance_available_at_period_end": true,
          "status": "exiting_online",
          "validator_index": 1674869,
          "withdrawable_epoch": 452937
        },
        {
          "balance_eth": "32.005589325",
          "balance_gwei": "32005589325",
          "effective_balance_eth": "32",
          "effective_balance_gwei": "32000000000",
          "full_balance_available_at_period_end": true,
          "status": "exiting_online",
          "validator_index": 1678170,
          "withdrawable_epoch": 452938
        }
      ],
      "exits_eth": "4994.097769942",
      "full_withdrawal_validators": 156,
      "label": "06-10",
      "queued_exit_validators": 3,
      "rewards_eth": "3017.410934628",
      "target_datetime": "2026-06-10T12:21:35Z",
      "total_eth": "8011.508704570",
      "validators": 238096
    },
    {
      "exit_validators": 156,
      "exited_validators": 153,
      "exiting_validators": [
        {
          "balance_eth": "32.005615441",
          "balance_gwei": "32005615441",
          "effective_balance_eth": "32",
          "effective_balance_gwei": "32000000000",
          "full_balance_available_at_period_end": true,
          "status": "exiting_online",
          "validator_index": 1674865,
          "withdrawable_epoch": 452937
        },
        {
          "balance_eth": "32.005619685",
          "balance_gwei": "32005619685",
          "effective_balance_eth": "32",
          "effective_balance_gwei": "32000000000",
          "full_balance_available_at_period_end": true,
          "status": "exiting_online",
          "validator_index": 1674869,
          "withdrawable_epoch": 452937
        },
        {
          "balance_eth": "32.005589325",
          "balance_gwei": "32005589325",
          "effective_balance_eth": "32",
          "effective_balance_gwei": "32000000000",
          "full_balance_available_at_period_end": true,
          "status": "exiting_online",
          "validator_index": 1678170,
          "withdrawable_epoch": 452938
        }
      ],
      "exits_eth": "4994.097769942",
      "full_withdrawal_validators": 156,
      "label": "06-11",
      "queued_exit_validators": 3,
      "rewards_eth": "3064.531442968",
      "target_datetime": "2026-06-11T12:21:35Z",
      "total_eth": "8058.629212910",
      "validators": 248838
    },
    {
      "exit_validators": 156,
      "exited_validators": 153,
      "exiting_validators": [
        {
          "balance_eth": "32.005615441",
          "balance_gwei": "32005615441",
          "effective_balance_eth": "32",
          "effective_balance_gwei": "32000000000",
          "full_balance_available_at_period_end": true,
          "status": "exiting_online",
          "validator_index": 1674865,
          "withdrawable_epoch": 452937
        },
        {
          "balance_eth": "32.005619685",
          "balance_gwei": "32005619685",
          "effective_balance_eth": "32",
          "effective_balance_gwei": "32000000000",
          "full_balance_available_at_period_end": true,
          "status": "exiting_online",
          "validator_index": 1674869,
          "withdrawable_epoch": 452937
        },
        {
          "balance_eth": "32.005589325",
          "balance_gwei": "32005589325",
          "effective_balance_eth": "32",
          "effective_balance_gwei": "32000000000",
          "full_balance_available_at_period_end": true,
          "status": "exiting_online",
          "validator_index": 1678170,
          "withdrawable_epoch": 452938
        }
      ],
      "exits_eth": "4994.097769942",
      "full_withdrawal_validators": 156,
      "label": "06-12",
      "queued_exit_validators": 3,
      "rewards_eth": "3083.989987293",
      "target_datetime": "2026-06-12T12:21:35Z",
      "total_eth": "8078.087757235",
      "validators": 259143
    }
  ],
  "refresh_interval_seconds": 600
}
